eFISHent/__init__.py
eFISHent/__main__.py
eFISHent/alignment.py
eFISHent/analyze.py
eFISHent/basic_filtering.py
eFISHent/cleanup.py
eFISHent/cli.py
eFISHent/config.py
eFISHent/console.py
eFISHent/constants.py
eFISHent/generate_probes.py
eFISHent/indexing.py
eFISHent/kmers.py
eFISHent/luigi.cfg
eFISHent/optimization.py
eFISHent/prepare_sequence.py
eFISHent/secondary_structure.py
eFISHent/util.py
eFISHent/data_tables/b-test.coaxial.dg
eFISHent/data_tables/b-test.coaxial.dh
eFISHent/data_tables/b-test.coaxstack.dg
eFISHent/data_tables/b-test.coaxstack.dh
eFISHent/data_tables/b-test.dangle.dg
eFISHent/data_tables/b-test.dangle.dh
eFISHent/data_tables/b-test.dynalignmiscloop.dg
eFISHent/data_tables/b-test.hexaloop.dg
eFISHent/data_tables/b-test.hexaloop.dh
eFISHent/data_tables/b-test.int11.dg
eFISHent/data_tables/b-test.int11.dh
eFISHent/data_tables/b-test.int21.dg
eFISHent/data_tables/b-test.int21.dh
eFISHent/data_tables/b-test.int22.dg
eFISHent/data_tables/b-test.int22.dh
eFISHent/data_tables/b-test.loop.dg
eFISHent/data_tables/b-test.miscloop.dg
eFISHent/data_tables/b-test.miscloop.dh
eFISHent/data_tables/b-test.specification.dat
eFISHent/data_tables/b-test.stack.dg
eFISHent/data_tables/b-test.stack.dh
eFISHent/data_tables/b-test.tloop.dg
eFISHent/data_tables/b-test.tloop.dh
eFISHent/data_tables/b-test.triloop.dg
eFISHent/data_tables/b-test.triloop.dh
eFISHent/data_tables/b-test.tstack.dg
eFISHent/data_tables/b-test.tstack.dh
eFISHent/data_tables/b-test.tstackcoax.dg
eFISHent/data_tables/b-test.tstackcoax.dh
eFISHent/data_tables/b-test.tstackh.dg
eFISHent/data_tables/b-test.tstackh.dh
eFISHent/data_tables/b-test.tstacki.dg
eFISHent/data_tables/b-test.tstacki.dh
eFISHent/data_tables/b-test.tstacki1n.dg
eFISHent/data_tables/b-test.tstacki1n.dh
eFISHent/data_tables/b-test.tstacki23.dg
eFISHent/data_tables/b-test.tstacki23.dh
eFISHent/data_tables/b-test.tstackm.dg
eFISHent/data_tables/b-test.tstackm.dh
eFISHent/data_tables/coaxial.dat
eFISHent/data_tables/coaxial.dh
efishent-0.0.7.dist-info/METADATA
efishent-0.0.7.dist-info/WHEEL
efishent-0.0.7.dist-info/entry_points.txt
efishent-0.0.7.dist-info/top_level.txt
efishent-0.0.7.dist-info/RECORD
