Metadata-Version: 2.4
Name: eFISHent
Version: 0.0.7
Summary: RNA FISH oligos/probes design tool.
Home-page: https://github.com/bbquercus/efishent/
Author: Bastian Eichenberger
Author-email: Bastian Eichenberger <bastian@eichenbergers.ch>
License-Expression: MIT
Project-URL: Homepage, https://github.com/bbquercus/efishent/
Project-URL: Documentation, https://github.com/BBQuercus/efishent/wiki
Project-URL: Changelog, https://github.com/BBQuercus/efishent/releases
Project-URL: Issue Tracker, https://github.com/bbquercus/efishent/issues
Keywords: biomedical,bioinformatics,RNA probe design
Classifier: Development Status :: 3 - Alpha
Classifier: Environment :: Console
Classifier: Intended Audience :: Developers
Classifier: Intended Audience :: Science/Research
Classifier: Operating System :: MacOS
Classifier: Operating System :: Microsoft :: Windows
Classifier: Operating System :: POSIX
Classifier: Operating System :: Unix
Classifier: Programming Language :: Python :: 3 :: Only
Classifier: Programming Language :: Python
Classifier: Topic :: Scientific/Engineering :: Bio-Informatics
Classifier: Topic :: Utilities
Requires-Python: >=3.8
Requires-Dist: biopython
Requires-Dist: gtfparse
Requires-Dist: luigi
Requires-Dist: matplotlib
Requires-Dist: numpy
Requires-Dist: pandas
Requires-Dist: pyarrow>=18.0.0
Requires-Dist: pyomo
Requires-Dist: pysam
Requires-Dist: rich>=13.0.0
Requires-Dist: rich-argparse>=1.4.0
Dynamic: author
Dynamic: home-page
Dynamic: requires-python
